MANIFEST.in
README.md
requirements.txt
setup.cfg
setup.py
maxlike/__init__.py
maxlike/maxlike.py
maxlike/maxlike_base.py
maxlike/numeric.py
maxlike/preprocessing.py
maxlike.egg-info/PKG-INFO
maxlike.egg-info/SOURCES.txt
maxlike.egg-info/dependency_links.txt
maxlike.egg-info/requires.txt
maxlike.egg-info/top_level.txt
maxlike/analytics/__init__.py
maxlike/analytics/kelly.py
maxlike/analytics/linear_regression.py
maxlike/analytics/missing_data.py
maxlike/analytics/proba.py
maxlike/analytics/skellam.py
maxlike/func/__init__.py
maxlike/func/copula.py
maxlike/func/func.py
maxlike/func/func_base.py
maxlike/func/func_op.py
maxlike/func/func_proba.py
maxlike/func/matrix.py
maxlike/func/sigmoid.py
maxlike/func/tennis.py
maxlike/tensor/__init__.py
maxlike/tensor/ctensor.pyx
maxlike/tensor/tensor.py
tests/maxlike/tensor/ctensor.pyx