Metadata-Version: 2.1
Name: maxlike
Version: 2.3.6
Summary: Python package to model count data
Home-page: https://github.com/jpceia/maxlike
Author: joao ceia
Author-email: joao.p.ceia@gmail.com
License: nolicense
Platform: UNKNOWN
Classifier: Development Status :: 4 - Beta
Classifier: Intended Audience :: Science/Research
Classifier: Topic :: Scientific/Engineering :: Mathematics
Classifier: Programming Language :: Python :: 3.5
Classifier: Programming Language :: Python :: 3.6
Classifier: Programming Language :: Python :: 3.7
